slack_notifier/__init__.py
slack_notifier/config.py
slack_notifier/slack_notifier.py
slack_notifier/version.py
slack_notifier-1.0.0.dist-info/DESCRIPTION.rst
slack_notifier-1.0.0.dist-info/METADATA
slack_notifier-1.0.0.dist-info/RECORD
slack_notifier-1.0.0.dist-info/WHEEL
slack_notifier-1.0.0.dist-info/entry_points.txt
slack_notifier-1.0.0.dist-info/metadata.json
slack_notifier-1.0.0.dist-info/top_level.txt
