Metadata-Version: 2.0
Name: slack-notifier
Version: 1.0.0
Summary: Supervisord Slack Notifier
Home-page: https://github.com/WoLpH/supervisord-slack-notifier
Author: Rick van Hattem
Author-email: Wolph@wol.ph
License: MIT License
Keywords: supervisord slack listener notifications
Platform: UNKNOWN
Requires-Dist: pyslack-real (==0.5.3)
Requires-Dist: supervisor
